LICENSE
MANIFEST.in
README.md
requirements.txt
setup.cfg
setup.py
exatomic/__init__.py
exatomic/_version.py
exatomic/base.py
exatomic/formula.py
exatomic/mpl.py
exatomic/static.py
exatomic.egg-info/PKG-INFO
exatomic.egg-info/SOURCES.txt
exatomic.egg-info/dependency_links.txt
exatomic.egg-info/not-zip-safe
exatomic.egg-info/requires.txt
exatomic.egg-info/top_level.txt
exatomic/adf/__init__.py
exatomic/adf/editor.py
exatomic/adf/inputs.py
exatomic/adf/output.py
exatomic/adf/tape21.py
exatomic/adf/adf/__init__.py
exatomic/adf/adf/adf.py
exatomic/adf/adf/geometry.py
exatomic/adf/adf/output.py
exatomic/adf/adf/scf.py
exatomic/adf/dirac/__init__.py
exatomic/adf/dirac/dirac.py
exatomic/adf/nmr/__init__.py
exatomic/adf/nmr/output.py
exatomic/adf/nmr/tests/__init__.py
exatomic/adf/nmr/tests/test_output.py
exatomic/adf/tests/__init__.py
exatomic/adf/tests/test_editor.py
exatomic/adf/tests/test_output.py
exatomic/adf/tests/test_tape21.py
exatomic/algorithms/__init__.py
exatomic/algorithms/angles.py
exatomic/algorithms/basis.py
exatomic/algorithms/car2sph.py
exatomic/algorithms/delocalization.py
exatomic/algorithms/diffusion.py
exatomic/algorithms/displacement.py
exatomic/algorithms/distance.py
exatomic/algorithms/geometry.py
exatomic/algorithms/harmonics.py
exatomic/algorithms/indexing.py
exatomic/algorithms/interpolation.py
exatomic/algorithms/neighbors.py
exatomic/algorithms/numerical.py
exatomic/algorithms/orbital.py
exatomic/algorithms/orbital_util.py
exatomic/algorithms/overlap.py
exatomic/algorithms/packing.py
exatomic/algorithms/pcf.py
exatomic/algorithms/tests/__init__.py
exatomic/algorithms/tests/test_basis.py
exatomic/algorithms/tests/test_distance.py
exatomic/algorithms/tests/test_geometry.py
exatomic/algorithms/tests/test_numerical.py
exatomic/algorithms/tests/test_orbital.py
exatomic/algorithms/tests/test_overlap.py
exatomic/conf/logging.yml
exatomic/core/__init__.py
exatomic/core/atom.py
exatomic/core/basis.py
exatomic/core/editor.py
exatomic/core/error.py
exatomic/core/field.py
exatomic/core/frame.py
exatomic/core/gradient.py
exatomic/core/matrices.py
exatomic/core/molecule.py
exatomic/core/orbital.py
exatomic/core/tensor.py
exatomic/core/two.py
