Metadata-Version: 2.1
Name: exatomic
Version: 0.6.0
Summary: A unified platform for theoretical and computational chemists.
Home-page: https://github.com/exa-analytics/exatomic
Download-URL: https://pypi.io/packages/source/e/exatomic/exatomic-0.6.0.tar.gz
Author: Thomas J. Duignan, Alex Marchenko and contributors
Author-email: exa.data.analytics@gmail.com
Maintainer-email: exa.data.analytics@gmail.com
License: Apache License Version 2.0
Keywords: quantum chemistry,jupyter notebook,visualization
Classifier: Development Status :: 4 - Beta
Classifier: Environment :: Web Environment
Classifier: Intended Audience :: Developers
Classifier: Intended Audience :: Science/Research
Classifier: License :: OSI Approved :: Apache Software License
Classifier: Programming Language :: Python :: 3
Classifier: Natural Language :: English
License-File: LICENSE
